pipableai/__init__.py
pipableai/pipable.py
pipableai/core/__init__.py
pipableai/core/dev_logger.py
pipableai/core/postgresql_connector.py
pipableai/interfaces/__init__.py
pipableai/interfaces/database_connector_interface.py
pipableai/interfaces/llm_api_client_interface.py
pipableai/llm_client/__init__.py
pipableai/llm_client/pipllm.py
pipableai-0.1.4.dist-info/LICENSE
pipableai-0.1.4.dist-info/METADATA
pipableai-0.1.4.dist-info/NOTICE
pipableai-0.1.4.dist-info/WHEEL
pipableai-0.1.4.dist-info/top_level.txt
pipableai-0.1.4.dist-info/RECORD
