Metadata-Version: 2.1
Name: pipableai
Version: 0.1.4
Summary: Simplify the process of connecting to remote PostgreSQL servers and executing natural language-based data search queries.
Home-page: UNKNOWN
Author: PipableAI
Author-email: dev@pipable.ai
License: UNKNOWN
Project-URL: HomePage, https://pipable.ai/
Project-URL: Documentation, https://pipableai.github.io/pipable-docs/
Project-URL: Source Code, https://github.com/PipableAI/pipable-open-source/tree/main/pipableAI
Project-URL: Issue Tracker, https://github.com/PipableAI/pipable-open-source/issues
Platform: UNKNOWN
Classifier: Programming Language :: Python :: 3.7
Classifier: License :: OSI Approved :: Apache Software License
Classifier: Operating System :: OS Independent
Requires-Python: >=3.7
License-File: LICENSE
License-File: NOTICE
Requires-Dist: pandas (>=2.0.0)
Requires-Dist: psycopg2-binary (<=2.9.9,>=2.9.0)
Requires-Dist: requests (>=2.28)
